athena_tools/__init__.py
athena_tools/athena_tools.py
athena_tools-0.0.1.dist-info/WHEEL
athena_tools-0.0.1.dist-info/METADATA
athena_tools-0.0.1.dist-info/RECORD
