Metadata-Version: 2.1
Name: athena-tools
Version: 0.0.1
Summary: set of useful Athena db creation tools
License: MIT
Author: stephen bias
Author-email: stephen.bias@digital.justice.gov.uk
Requires-Python: >=3.7.1,<3.10
Classifier: License :: OSI Approved :: MIT License
Classifier: Programming Language :: Python :: 3
Classifier: Programming Language :: Python :: 3.8
Classifier: Programming Language :: Python :: 3.9
Requires-Dist: arrow-pd-parser (>=1.0.4,<2.0.0)
Requires-Dist: dataengineeringutils3 (>=1.4.0,<2.0.0)
Requires-Dist: mojap-metadata[glue,arrow] (>=1.9.4,<2.0.0)
Requires-Dist: pydbtools (>=5.2.0,<6.0.0)
